greeting/__init__.py
wbswjc/__init__.py
wbswjc/greeting/__init__.py
wbswjc_greeting-0.0.4.dist-info/LICENSE
wbswjc_greeting-0.0.4.dist-info/METADATA
wbswjc_greeting-0.0.4.dist-info/WHEEL
wbswjc_greeting-0.0.4.dist-info/top_level.txt
wbswjc_greeting-0.0.4.dist-info/RECORD
